{
  "catalog": {
    "description": "Jafar - JFR analysis tools",
    "repository": "https://github.com/btraceio/jbang-catalog"
  },
  "aliases": {
    "jfr-shell": {
      "script-ref": "jfr-shell.java",
      "description": "Interactive CLI for exploring and analyzing Java Flight Recorder files with JfrPath query language"
    },
    "jfr-shell-latest": {
      "script-ref": "io.btrace:jafar-shell:0.3.10",
      "description": "JFR Shell latest stable version from Maven Central",
      "java": "21+"
    }
  }
}
